droplets.py
droplets-1.3.0.dist-info/METADATA
droplets-1.3.0.dist-info/WHEEL
droplets-1.3.0.dist-info/top_level.txt
droplets-1.3.0.dist-info/RECORD
