Metadata-Version: 2.1
Name: droplets
Version: 1.3.0
Summary: Library for building Ansible dynamic inventories for Digital Ocean.
Home-page: http://github.com/chrisrossi/droplets
Author: Chris Rossi
Author-email: chris@armchimedeanco.com
License: BSD-derived (http://www.repoze.org/LICENSE.txt)
Platform: UNKNOWN
Classifier: Development Status :: 5 - Production/Stable
Classifier: Intended Audience :: Developers
Classifier: Programming Language :: Python
Classifier: Programming Language :: Python :: 2.7
Classifier: Programming Language :: Python :: 3.5
Classifier: Programming Language :: Python :: 3.6
Classifier: Programming Language :: Python :: 3.7
Classifier: Programming Language :: Python :: 3.8
Classifier: Programming Language :: Python :: 3.9
Classifier: Programming Language :: Python :: Implementation :: CPython
Classifier: License :: Repoze Public License
Requires-Dist: docopt
Requires-Dist: ndg-httpsclient
Requires-Dist: pyasn1
Requires-Dist: pyopenssl
Requires-Dist: requests
